eodatasets3/__init__.py
eodatasets3/_version.py
eodatasets3/assemble.py
eodatasets3/dataset.schema.yaml
eodatasets3/documents.py
eodatasets3/images.py
eodatasets3/model.py
eodatasets3/names.py
eodatasets3/properties.py
eodatasets3/py.typed
eodatasets3/serialise.py
eodatasets3/stac.py
eodatasets3/ui.py
eodatasets3/utils.py
eodatasets3/validate.py
eodatasets3/verify.py
eodatasets3/wagl.py
eodatasets3/metadata/__init__.py
eodatasets3/metadata/valid_region.py
eodatasets3/prepare/__init__.py
eodatasets3/prepare/esri_land_cover_prepare.py
eodatasets3/prepare/landsat_l1_prepare.py
eodatasets3/prepare/nasa_c_m_mcd43a1_6_prepare.py
eodatasets3/prepare/noaa_c_c_prwtreatm_1_prepare.py
eodatasets3/prepare/s2_common.py
eodatasets3/prepare/s2_regions.db
eodatasets3/prepare/sentinel_l1_prepare.py
eodatasets3/scripts/__init__.py
eodatasets3/scripts/packagewagl.py
eodatasets3/scripts/prepare.py
eodatasets3/scripts/recompress.py
eodatasets3/scripts/tostac.py
eodatasets3-1.9.3.dist-info/licenses/LICENSE
eodatasets3-1.9.3.dist-info/METADATA
eodatasets3-1.9.3.dist-info/WHEEL
eodatasets3-1.9.3.dist-info/entry_points.txt
eodatasets3-1.9.3.dist-info/top_level.txt
eodatasets3-1.9.3.dist-info/RECORD
