Metadata-Version: 2.4
Name: eodatasets3
Version: 1.9.3
Summary: Packaging, metadata and provenance for OpenDataCube EO3 datasets
Author: Open Data Cube
License-Expression: Apache-2.0
Project-URL: Bug Reports, https://github.com/opendatacube/eo-datasets/issues
Project-URL: Source, https://github.com/opendatacube/eo-datasets
Classifier: Programming Language :: Python :: 3
Classifier: Programming Language :: Python :: 3.10
Classifier: Programming Language :: Python :: 3.11
Classifier: Programming Language :: Python :: 3.12
Classifier: Operating System :: OS Independent
Requires-Python: >=3.10
License-File: LICENSE
Requires-Dist: affine
Requires-Dist: attrs>=18.1
Requires-Dist: boltons
Requires-Dist: botocore
Requires-Dist: boto3
Requires-Dist: cattrs
Requires-Dist: ciso8601
Requires-Dist: click
Requires-Dist: defusedxml
Requires-Dist: fiona
Requires-Dist: h5py
Requires-Dist: jsonschema>=4.18
Requires-Dist: numpy>=1.15.4
Requires-Dist: pyproj
Requires-Dist: rasterio
Requires-Dist: ruamel.yaml
Requires-Dist: scipy
Requires-Dist: shapely
Requires-Dist: structlog
Requires-Dist: xarray
Requires-Dist: datacube>=1.9.0
Requires-Dist: pystac>=1.8.4
Provides-Extra: algorithms
Requires-Dist: scikit-image; extra == "algorithms"
Provides-Extra: ancillary
Requires-Dist: checksumdir; extra == "ancillary"
Requires-Dist: netCDF4; extra == "ancillary"
Provides-Extra: wagl
Requires-Dist: h5py; extra == "wagl"
Provides-Extra: all
Requires-Dist: checksumdir; extra == "all"
Requires-Dist: netCDF4; extra == "all"
Requires-Dist: deepdiff>=8.0; extra == "all"
Requires-Dist: h5py; extra == "all"
Requires-Dist: mock; extra == "all"
Requires-Dist: pystac>=1.12; extra == "all"
Requires-Dist: pytest-cov; extra == "all"
Requires-Dist: pytest-xdist; extra == "all"
Requires-Dist: pytest; extra == "all"
Requires-Dist: rio_cogeo; extra == "all"
Requires-Dist: ruff; extra == "all"
Requires-Dist: scikit-image; extra == "all"
Requires-Dist: sphinx_rtd_theme; extra == "all"
Requires-Dist: sphinx-autodoc-typehints; extra == "all"
Provides-Extra: test
Requires-Dist: checksumdir; extra == "test"
Requires-Dist: netCDF4; extra == "test"
Requires-Dist: deepdiff>=8.0; extra == "test"
Requires-Dist: h5py; extra == "test"
Requires-Dist: mock; extra == "test"
Requires-Dist: pystac>=1.12; extra == "test"
Requires-Dist: pytest-cov; extra == "test"
Requires-Dist: pytest-xdist; extra == "test"
Requires-Dist: pytest; extra == "test"
Requires-Dist: rio_cogeo; extra == "test"
Requires-Dist: ruff; extra == "test"
Requires-Dist: scikit-image; extra == "test"
Requires-Dist: sphinx_rtd_theme; extra == "test"
Requires-Dist: sphinx-autodoc-typehints; extra == "test"
Provides-Extra: deployment
Requires-Dist: h5py; extra == "deployment"
Dynamic: license-file
